{"chunk_definitions":[{"chunk_id":"cp9oyfy2riibt","expansion_state":0,"options":[],"row":9,"row_count":1,"visible":true},{"chunk_id":"cwoqktq1kgwqr","expansion_state":0,"options":[],"row":22,"row_count":1,"visible":true},{"chunk_id":"c77huvjt526rj","expansion_state":0,"options":[],"row":41,"row_count":1,"visible":true},{"chunk_id":"cucuf4jt25q20","expansion_state":0,"options":[],"row":56,"row_count":1,"visible":true},{"chunk_id":"c17jlhx746vy1","expansion_state":0,"options":[],"row":77,"row_count":1,"visible":true}],"doc_write_time":1696150237.44395}
